fatoriais/__init__.py
fatoriais/fatorial.py
fatoriais-0.0.1.dist-info/METADATA
fatoriais-0.0.1.dist-info/WHEEL
fatoriais-0.0.1.dist-info/top_level.txt
fatoriais-0.0.1.dist-info/RECORD
