Metadata-Version: 2.4
Name: fatoriais
Version: 0.0.1
Summary: Calcula o fatorial de um número inteiro não negativo.
Home-page: https://github.com/Enzo-Camelo/simple-package-template.git
Author: Enzo Camelo
Author-email: enzocamelo8d@gmail.com
Requires-Python: >=3.8
Dynamic: author
Dynamic: author-email
Dynamic: description
Dynamic: description-content-type
Dynamic: home-page
Dynamic: requires-python
Dynamic: summary
